{
    "instance_name": "Lera-RC2_10_1-S1",
    "instance_origin": "GehHom1999",
    "benchmark_name": "Lera2026",
    "num_customers": 1000,
    "num_vehicles": 250,
    "vehicle_capacity": 1000,
    "coordinates": [
        [250, 250],
        [440, 436],
        [214, 394],
        [476, 483],
        [352, 487],
        [230, 197],
        [175, 239],
        [133, 202],
        [328, 458],
        [25, 499],
        [226, 423],
        [313, 282],
        [60, 454],
        [239, 486],
        [102, 264],
        [408, 452],
        [451, 62],
        [203, 390],
        [92, 233],
        [7, 300],
        [409, 90],
        [307, 108],
        [347, 54],
        [406, 87],
        [371, 332],
        [116, 466],
        [441, 265],
        [130, 140],
        [80, 117],
        [421, 387],
        [83, 300],
        [136, 52],
        [18, 462],
        [390, 120],
        [188, 119],
        [467, 114],
        [440, 292],
        [268, 400],
        [391, 202],
        [377, 432],
        [80, 290],
        [439, 15],
        [307, 52],
        [111, 192],
        [131, 56],
        [88, 286],
        [69, 414],
        [41, 232],
        [323, 77],
        [340, 416],
        [86, 199],
        [314, 124],
        [375, 191],
        [226, 175],
        [242, 106],
        [417, 417],
        [419, 459],
        [389, 11],
        [450, 416],
        [246, 255],
        [71, 333],
        [105, 474],
        [20, 489],
        [388, 331],
        [92, 259],
        [200, 261],
        [400, 288],
        [299, 285],
        [378, 199],
        [325, 147],
        [421, 386],
        [404, 447],
        [412, 478],
        [26, 67],
        [358, 183],
        [30, 302],
        [176, 470],
        [96, 270],
        [243, 408],
        [60, 29],
        [34, 169],
        [407, 280],
        [277, 403],
        [498, 456],
        [384, 491],
        [355, 174],
        [97, 288],
        [316, 284],
        [334, 403],
        [415, 223],
        [230, 320],
        [432, 199],
        [92, 18],
        [273, 300],
        [269, 112],
        [429, 389],
        [371, 71],
        [5, 297],
        [414, 378],
        [38, 15],
        [2, 295],
        [237, 254],
        [54, 445],
        [382, 110],
        [438, 488],
        [395, 331],
        [230, 487],
        [249, 407],
        [488, 26],
        [151, 81],
        [483, 14],
        [0, 422],
        [429, 67],
        [195, 464],
        [356, 256],
        [264, 180],
        [94, 235],
        [474, 96],
        [268, 52],
        [44, 440],
        [7, 382],
        [459, 53],
        [491, 25],
        [439, 243],
        [210, 185],
        [150, 68],
        [201, 270],
        [0, 188],
        [103, 464],
        [325, 56],
        [44, 344],
        [418, 75],
        [472, 57],
        [460, 328],
        [89, 270],
        [374, 190],
        [463, 253],
        [97, 93],
        [163, 472],
        [29, 336],
        [84, 453],
        [294, 421],
        [343, 62],
        [371, 193],
        [142, 372],
        [66, 88],
        [395, 332],
        [93, 413],
        [267, 394],
        [249, 258],
        [472, 129],
        [87, 3],
        [62, 326],
        [212, 186],
        [241, 402],
        [439, 266],
        [79, 80],
        [62, 453],
        [188, 151],
        [386, 154],
        [38, 301],
        [192, 265],
        [371, 192],
        [64, 294],
        [381, 494],
        [437, 12],
        [186, 135],
        [459, 10],
        [175, 422],
        [274, 48],
        [488, 173],
        [398, 97],
        [385, 17],
        [180, 283],
        [71, 12],
        [343, 49],
        [248, 251],
        [7, 194],
        [322, 290],
        [410, 399],
        [398, 103],
        [385, 285],
        [179, 497],
        [464, 13],
        [492, 335],
        [27, 464],
        [231, 29],
        [157, 38],
        [439, 268],
        [149, 214],
        [187, 73],
        [429, 169],
        [350, 199],
        [60, 231],
        [448, 404],
        [481, 20],
        [436, 25],
        [111, 459],
        [389, 17],
        [148, 208],
        [475, 477],
        [390, 325],
        [346, 354],
        [91, 266],
        [17, 65],
        [391, 112],
        [224, 203],
        [426, 231],
        [260, 472],
        [265, 0],
        [391, 293],
        [411, 421],
        [132, 30],
        [475, 480],
        [286, 244],
        [436, 237],
        [402, 284],
        [287, 397],
        [272, 420],
        [477, 120],
        [145, 434],
        [33, 286],
        [370, 262],
        [393, 20],
        [330, 308],
        [246, 398],
        [482, 184],
        [451, 305],
        [226, 316],
        [110, 459],
        [244, 250],
        [458, 16],
        [390, 34],
        [423, 214],
        [219, 215],
        [326, 118],
        [365, 74],
        [331, 356],
        [210, 398],
        [403, 93],
        [248, 404],
        [65, 62],
        [460, 13],
        [0, 293],
        [211, 248],
        [484, 174],
        [175, 352],
        [455, 168],
        [224, 191],
        [439, 156],
        [434, 359],
        [118, 314],
        [234, 246],
        [406, 450],
        [75, 118],
        [115, 395],
        [329, 456],
        [218, 403],
        [149, 341],
        [253, 74],
        [436, 241],
        [238, 203],
        [405, 455],
        [485, 27],
        [323, 118],
        [330, 371],
        [25, 65],
        [406, 96],
        [49, 451],
        [307, 249],
        [178, 135],
        [299, 353],
        [236, 213],
        [355, 177],
        [394, 23],
        [306, 235],
        [90, 477],
        [379, 486],
        [435, 16],
        [8, 497],
        [150, 484],
        [213, 399],
        [391, 18],
        [111, 392],
        [330, 281],
        [344, 203],
        [91, 235],
        [346, 60],
        [483, 27],
        [382, 498],
        [457, 492],
        [291, 213],
        [154, 374],
        [225, 196],
        [94, 40],
        [0, 356],
        [297, 283],
        [371, 423],
        [417, 217],
        [500, 228],
        [412, 214],
        [442, 289],
        [157, 269],
        [440, 241],
        [100, 266],
        [111, 178],
        [91, 101],
        [25, 307],
        [135, 400],
        [58, 458],
        [133, 26],
        [211, 386],
        [94, 97],
        [30, 155],
        [208, 184],
        [394, 333],
        [355, 180],
        [241, 180],
        [21, 485],
        [80, 251],
        [476, 61],
        [406, 94],
        [364, 71],
        [418, 221],
        [274, 441],
        [304, 97],
        [297, 102],
        [250, 405],
        [111, 463],
        [408, 279],
        [263, 418],
        [480, 119],
        [420, 383],
        [142, 14],
        [73, 328],
        [50, 438],
        [441, 7],
        [462, 14],
        [360, 294],
        [58, 39],
        [58, 391],
        [410, 285],
        [96, 97],
        [21, 64],
        [238, 210],
        [479, 121],
        [200, 178],
        [216, 341],
        [48, 437],
        [200, 270],
        [357, 181],
        [476, 174],
        [400, 286],
        [351, 481],
        [270, 400],
        [95, 234],
        [128, 113],
        [133, 455],
        [16, 463],
        [59, 388],
        [376, 190],
        [481, 122],
        [266, 405],
        [374, 232],
        [398, 20],
        [481, 26],
        [63, 444],
        [89, 290],
        [246, 314],
        [40, 304],
        [262, 369],
        [323, 29],
        [89, 65],
        [144, 35],
        [200, 265],
        [436, 264],
        [15, 457],
        [397, 20],
        [328, 491],
        [399, 175],
        [432, 2],
        [63, 336],
        [6, 296],
        [146, 376],
        [295, 247],
        [235, 33],
        [233, 204],
        [142, 360],
        [177, 156],
        [315, 287],
        [452, 172],
        [263, 153],
        [493, 493],
        [320, 283],
        [64, 5],
        [95, 235],
        [203, 211],
        [16, 497],
        [348, 348],
        [485, 104],
        [330, 147],
        [443, 237],
        [316, 286],
        [335, 46],
        [381, 495],
        [364, 173],
        [267, 162],
        [214, 245],
        [92, 234],
        [347, 459],
        [30, 7],
        [120, 37],
        [397, 153],
        [210, 29],
        [87, 285],
        [132, 32],
        [390, 294],
        [67, 451],
        [24, 68],
        [146, 439],
        [209, 212],
        [6, 292],
        [18, 63],
        [149, 98],
        [91, 268],
        [103, 177],
        [367, 178],
        [225, 269],
        [443, 246],
        [306, 42],
        [374, 306],
        [413, 421],
        [470, 405],
        [33, 278],
        [149, 458],
        [257, 57],
        [272, 403],
        [221, 291],
        [1, 101],
        [332, 459],
        [220, 392],
        [253, 50],
        [250, 441],
        [471, 484],
        [480, 152],
        [404, 83],
        [476, 94],
        [458, 213],
        [215, 395],
        [85, 288],
        [179, 75],
        [228, 287],
        [397, 18],
        [238, 204],
        [488, 3],
        [407, 88],
        [459, 14],
        [120, 17],
        [235, 316],
        [370, 382],
        [405, 454],
        [17, 458],
        [43, 135],
        [318, 497],
        [199, 268],
        [111, 467],
        [138, 438],
        [172, 314],
        [494, 468],
        [35, 303],
        [341, 59],
        [423, 221],
        [395, 295],
        [413, 417],
        [339, 60],
        [277, 428],
        [176, 199],
        [265, 240],
        [365, 190],
        [133, 53],
        [387, 488],
        [385, 295],
        [491, 369],
        [445, 273],
        [195, 273],
        [313, 493],
        [495, 227],
        [241, 403],
        [30, 72],
        [21, 487],
        [324, 99],
        [453, 318],
        [443, 272],
        [447, 184],
        [366, 288],
        [440, 284],
        [13, 314],
        [72, 227],
        [377, 385],
        [477, 478],
        [204, 185],
        [226, 191],
        [330, 138],
        [185, 434],
        [483, 22],
        [71, 282],
        [60, 5],
        [189, 402],
        [134, 211],
        [146, 313],
        [21, 146],
        [37, 281],
        [416, 417],
        [44, 311],
        [361, 181],
        [444, 242],
        [444, 271],
        [359, 179],
        [388, 334],
        [401, 164],
        [499, 316],
        [399, 106],
        [425, 215],
        [407, 98],
        [406, 460],
        [88, 95],
        [95, 64],
        [306, 229],
        [273, 55],
        [384, 149],
        [122, 35],
        [308, 199],
        [390, 301],
        [300, 108],
        [267, 400],
        [8, 300],
        [105, 181],
        [398, 325],
        [166, 247],
        [140, 431],
        [253, 118],
        [359, 246],
        [321, 277],
        [168, 59],
        [406, 285],
        [391, 334],
        [437, 19],
        [201, 278],
        [435, 267],
        [245, 408],
        [16, 462],
        [107, 374],
        [477, 97],
        [346, 57],
        [14, 459],
        [102, 6],
        [359, 287],
        [297, 131],
        [282, 1],
        [21, 70],
        [440, 244],
        [482, 104],
        [120, 261],
        [125, 29],
        [292, 32],
        [262, 92],
        [68, 160],
        [405, 276],
        [277, 50],
        [32, 319],
        [344, 70],
        [481, 84],
        [21, 68],
        [441, 244],
        [57, 43],
        [1, 293],
        [481, 96],
        [471, 368],
        [236, 126],
        [406, 99],
        [303, 186],
        [225, 369],
        [412, 453],
        [104, 349],
        [173, 182],
        [111, 464],
        [53, 440],
        [69, 336],
        [359, 182],
        [13, 459],
        [244, 277],
        [484, 177],
        [452, 206],
        [22, 483],
        [452, 110],
        [347, 192],
        [95, 92],
        [368, 311],
        [479, 387],
        [479, 169],
        [497, 266],
        [66, 336],
        [376, 195],
        [401, 281],
        [441, 177],
        [231, 203],
        [21, 488],
        [231, 204],
        [122, 422],
        [65, 453],
        [206, 261],
        [466, 149],
        [313, 119],
        [90, 274],
        [39, 162],
        [35, 306],
        [437, 15],
        [307, 412],
        [79, 291],
        [64, 437],
        [376, 92],
        [129, 27],
        [196, 489],
        [51, 286],
        [20, 488],
        [13, 455],
        [170, 347],
        [92, 230],
        [117, 467],
        [413, 217],
        [405, 450],
        [394, 322],
        [125, 61],
        [238, 123],
        [11, 403],
        [89, 272],
        [304, 102],
        [478, 121],
        [408, 84],
        [376, 494],
        [20, 73],
        [159, 299],
        [95, 382],
        [352, 63],
        [365, 274],
        [30, 301],
        [351, 5],
        [197, 267],
        [498, 171],
        [468, 352],
        [418, 251],
        [489, 437],
        [251, 63],
        [132, 55],
        [281, 96],
        [333, 293],
        [255, 487],
        [207, 400],
        [469, 489],
        [244, 254],
        [233, 207],
        [441, 60],
        [411, 379],
        [178, 72],
        [51, 447],
        [478, 118],
        [141, 426],
        [295, 89],
        [112, 433],
        [320, 211],
        [400, 103],
        [408, 453],
        [435, 180],
        [432, 66],
        [374, 116],
        [478, 102],
        [335, 57],
        [385, 239],
        [386, 245],
        [208, 396],
        [380, 489],
        [380, 498],
        [440, 7],
        [434, 245],
        [90, 232],
        [389, 334],
        [241, 205],
        [18, 24],
        [57, 183],
        [59, 457],
        [442, 243],
        [402, 281],
        [445, 237],
        [441, 273],
        [31, 175],
        [234, 202],
        [52, 303],
        [167, 445],
        [179, 286],
        [269, 48],
        [165, 59],
        [461, 8],
        [421, 415],
        [59, 459],
        [24, 492],
        [55, 449],
        [224, 192],
        [444, 269],
        [491, 20],
        [313, 126],
        [283, 438],
        [352, 241],
        [398, 476],
        [442, 247],
        [217, 207],
        [233, 87],
        [479, 127],
        [6, 53],
        [478, 300],
        [378, 493],
        [303, 78],
        [344, 62],
        [371, 315],
        [200, 78],
        [413, 391],
        [415, 216],
        [397, 57],
        [293, 228],
        [0, 297],
        [435, 20],
        [195, 111],
        [417, 218],
        [340, 54],
        [132, 57],
        [210, 379],
        [228, 260],
        [399, 104],
        [95, 277],
        [360, 284],
        [53, 466],
        [112, 465],
        [313, 391],
        [93, 235],
        [125, 32],
        [215, 282],
        [224, 320],
        [134, 428],
        [26, 490],
        [44, 115],
        [438, 127],
        [239, 15],
        [342, 54],
        [109, 463],
        [199, 187],
        [201, 188],
        [399, 301],
        [484, 171],
        [272, 234],
        [380, 350],
        [140, 108],
        [228, 199],
        [245, 461],
        [305, 107],
        [231, 195],
        [450, 265],
        [273, 149],
        [12, 358],
        [315, 121],
        [420, 213],
        [331, 134],
        [84, 377],
        [320, 280],
        [89, 185],
        [472, 481],
        [422, 420],
        [475, 267],
        [470, 125],
        [435, 268],
        [409, 155],
        [243, 248],
        [488, 96],
        [341, 72],
        [58, 449],
        [16, 460],
        [480, 136],
        [162, 388],
        [47, 208],
        [324, 127],
        [87, 96],
        [140, 137],
        [314, 205],
        [96, 346],
        [321, 280],
        [245, 251],
        [436, 295],
        [274, 261],
        [271, 128],
        [275, 45],
        [422, 409],
        [146, 188],
        [93, 96],
        [409, 255],
        [449, 428],
        [90, 285],
        [415, 95],
        [88, 287],
        [379, 196],
        [368, 452],
        [202, 186],
        [435, 11],
        [269, 46],
        [7, 292],
        [44, 496],
        [478, 99],
        [391, 99],
        [132, 477],
        [24, 65],
        [130, 247],
        [133, 273],
        [347, 62],
        [404, 140],
        [416, 420],
        [67, 335],
        [92, 270],
        [411, 95],
        [132, 479],
        [366, 334],
        [125, 39],
        [419, 422],
        [460, 2],
        [67, 334],
        [448, 414],
        [46, 163],
        [77, 465],
        [284, 319],
        [102, 422],
        [240, 34],
        [141, 428],
        [204, 269],
        [144, 439],
        [470, 417],
        [404, 103],
        [5, 281],
        [487, 320],
        [398, 23],
        [90, 296],
        [386, 13],
        [115, 465],
        [473, 475],
        [275, 42],
        [286, 356],
        [15, 69],
        [267, 44],
        [243, 399],
        [390, 249],
        [210, 391],
        [433, 15],
        [24, 259],
        [12, 463],
        [237, 213],
        [182, 480],
        [409, 88],
        [244, 368],
        [381, 328],
        [213, 185],
        [482, 141],
        [319, 124],
        [141, 431],
        [198, 264],
        [69, 334],
        [299, 98],
        [240, 250],
        [199, 203],
        [459, 17],
        [423, 217],
        [477, 179],
        [213, 397],
        [405, 187],
        [269, 402],
        [53, 204],
        [13, 394],
        [15, 68],
        [56, 268],
        [360, 184],
        [307, 102],
        [130, 57],
        [250, 328],
        [91, 231],
        [479, 176],
        [420, 224],
        [461, 182],
        [418, 218],
        [419, 418],
        [336, 493],
        [389, 300],
        [92, 76],
        [476, 102],
        [418, 399],
        [109, 56],
        [13, 465],
        [92, 232],
        [394, 47],
        [16, 287],
        [399, 102],
        [143, 158],
        [18, 484],
        [250, 411],
        [19, 273],
        [365, 28],
        [387, 297],
        [433, 447],
        [214, 274],
        [489, 338],
        [130, 494],
        [23, 67],
        [374, 489],
        [126, 30],
        [112, 467],
        [489, 274],
        [61, 214],
        [166, 440],
        [56, 75],
        [210, 276],
        [80, 286],
        [17, 459],
        [66, 448],
        [351, 128],
        [352, 176],
        [490, 286],
        [247, 219],
        [86, 268],
        [398, 329],
        [272, 402],
        [317, 123],
        [408, 318],
        [66, 31],
        [425, 448],
        [35, 304],
        [471, 94],
        [470, 473],
        [224, 56],
        [343, 47],
        [52, 18],
        [16, 68],
        [195, 185],
        [92, 236],
        [76, 462],
        [124, 56],
        [481, 454],
        [477, 483],
        [481, 124],
        [389, 156],
        [384, 16],
        [492, 34],
        [371, 200],
        [153, 235],
        [428, 202],
        [257, 391],
        [421, 218],
        [206, 186],
        [393, 301],
        [204, 187],
        [468, 475],
        [477, 122],
        [100, 66],
        [489, 27],
        [12, 451],
        [197, 270],
        [311, 422],
        [489, 17],
        [13, 214],
        [440, 247],
        [28, 467],
        [388, 325],
        [270, 401],
        [5, 445],
        [198, 271],
        [480, 131],
        [437, 98],
        [131, 246],
        [49, 437],
        [270, 49],
        [337, 41],
        [318, 280],
        [154, 392],
        [493, 111],
        [399, 450],
        [67, 452],
        [34, 239],
        [343, 276],
        [393, 12],
        [236, 247],
        [340, 291],
        [3, 292],
        [209, 68],
        [18, 225],
        [147, 435],
        [335, 99],
        [485, 24],
        [470, 475],
        [341, 58]
    ],
    "demands": [0, 18, 10, 10, 27, 40, 23, 33, 17, 10, 15, 20, 10, 3, 10, 10, 5, 40, 10, 30, 20, 10, 10, 10, 14, 20, 40, 17, 24, 15, 26, 10, 20, 24, 44, 10, 24, 20, 14, 20, 10, 20, 23, 11, 10, 10, 6, 16, 36, 36, 23, 20, 30, 23, 28, 10, 20, 20, 25, 10, 10, 27, 10, 20, 4, 10, 30, 3, 10, 14, 29, 20, 7, 15, 20, 10, 14, 20, 15, 32, 11, 10, 10, 27, 20, 33, 22, 20, 26, 20, 8, 7, 8, 30, 19, 18, 21, 10, 23, 3, 30, 20, 10, 24, 18, 20, 20, 10, 30, 28, 10, 8, 16, 20, 19, 33, 20, 30, 10, 24, 27, 20, 10, 20, 20, 23, 10, 26, 22, 13, 12, 11, 17, 13, 10, 20, 23, 20, 9, 22, 19, 26, 10, 20, 18, 2, 10, 17, 10, 30, 10, 13, 20, 11, 11, 10, 19, 10, 7, 31, 20, 10, 30, 12, 10, 20, 24, 10, 24, 10, 20, 10, 40, 23, 2, 10, 20, 29, 23, 25, 30, 13, 1, 20, 10, 21, 14, 3, 10, 7, 18, 8, 21, 32, 15, 20, 19, 20, 10, 22, 20, 30, 8, 10, 20, 24, 20, 24, 33, 10, 20, 20, 20, 30, 31, 20, 30, 12, 7, 10, 20, 11, 15, 20, 24, 40, 14, 13, 21, 30, 10, 20, 7, 20, 32, 10, 24, 13, 10, 10, 30, 15, 20, 30, 26, 10, 12, 21, 20, 2, 13, 26, 10, 20, 21, 11, 19, 15, 6, 20, 20, 10, 40, 10, 20, 1, 10, 20, 20, 10, 21, 34, 20, 20, 20, 25, 18, 22, 10, 40, 16, 18, 10, 18, 14, 14, 10, 10, 20, 10, 7, 23, 36, 10, 24, 13, 28, 10, 30, 8, 10, 25, 31, 10, 20, 18, 10, 10, 20, 10, 10, 20, 20, 9, 20, 20, 30, 13, 30, 14, 36, 10, 5, 10, 12, 20, 10, 20, 20, 20, 25, 7, 27, 18, 20, 20, 20, 20, 9, 12, 16, 20, 20, 20, 30, 10, 20, 19, 4, 20, 20, 30, 10, 10, 10, 10, 22, 25, 20, 20, 30, 30, 20, 33, 20, 30, 20, 20, 36, 16, 15, 7, 16, 26, 10, 20, 20, 20, 21, 13, 20, 20, 10, 8, 12, 30, 20, 20, 25, 30, 9, 12, 20, 30, 14, 10, 20, 20, 23, 21, 28, 20, 30, 18, 20, 30, 6, 8, 10, 25, 23, 28, 29, 13, 30, 18, 20, 5, 20, 10, 18, 10, 10, 4, 10, 28, 20, 30, 20, 11, 4, 10, 17, 18, 13, 18, 30, 9, 8, 35, 20, 27, 5, 10, 26, 30, 20, 22, 20, 20, 13, 21, 10, 20, 3, 10, 20, 30, 2, 11, 11, 10, 31, 21, 20, 20, 20, 9, 31, 20, 27, 9, 20, 10, 20, 7, 28, 9, 22, 20, 20, 20, 28, 20, 22, 20, 20, 10, 10, 10, 10, 30, 10, 27, 29, 25, 14, 25, 6, 20, 20, 20, 18, 9, 10, 29, 18, 10, 35, 22, 21, 17, 20, 27, 20, 10, 10, 20, 20, 13, 18, 20, 10, 10, 2, 20, 4, 10, 20, 18, 10, 14, 10, 10, 10, 10, 19, 30, 1, 30, 19, 18, 10, 6, 20, 20, 15, 13, 20, 10, 10, 8, 10, 20, 20, 3, 24, 25, 18, 15, 10, 19, 5, 30, 14, 25, 21, 20, 10, 21, 24, 17, 20, 10, 15, 10, 20, 19, 23, 20, 10, 38, 10, 20, 25, 10, 10, 20, 20, 20, 18, 20, 31, 30, 14, 18, 20, 14, 13, 20, 25, 10, 10, 20, 23, 20, 10, 20, 3, 30, 10, 16, 30, 20, 18, 20, 30, 8, 10, 11, 10, 10, 23, 14, 10, 10, 15, 20, 10, 20, 20, 12, 26, 24, 18, 10, 30, 40, 10, 30, 10, 12, 19, 6, 14, 10, 12, 10, 12, 9, 21, 29, 14, 10, 1, 27, 19, 20, 4, 20, 10, 21, 25, 23, 10, 20, 23, 23, 29, 16, 10, 10, 37, 30, 9, 10, 30, 21, 16, 20, 20, 10, 20, 10, 10, 20, 30, 32, 15, 30, 10, 20, 10, 20, 24, 10, 25, 7, 8, 20, 27, 20, 30, 20, 10, 20, 10, 20, 20, 10, 3, 5, 25, 10, 26, 18, 20, 8, 12, 30, 12, 10, 18, 31, 8, 10, 17, 19, 10, 20, 15, 10, 10, 20, 12, 12, 10, 20, 19, 9, 10, 5, 10, 30, 21, 36, 20, 10, 24, 2, 2, 20, 30, 20, 10, 30, 10, 26, 15, 29, 10, 8, 20, 20, 10, 14, 7, 10, 10, 11, 10, 10, 16, 20, 20, 7, 20, 10, 19, 30, 22, 9, 30, 20, 22, 11, 30, 30, 30, 32, 22, 26, 30, 10, 11, 20, 12, 20, 10, 6, 20, 23, 25, 40, 15, 30, 20, 16, 20, 40, 20, 10, 32, 10, 20, 25, 10, 17, 20, 10, 8, 20, 20, 20, 30, 11, 5, 20, 20, 20, 20, 23, 8, 11, 17, 23, 28, 20, 30, 30, 11, 20, 16, 21, 10, 20, 10, 10, 10, 30, 30, 10, 20, 10, 21, 30, 20, 19, 20, 10, 31, 20, 25, 12, 21, 14, 20, 30, 20, 30, 30, 10, 20, 20, 20, 20, 10, 34, 20, 8, 15, 10, 28, 10, 40, 40, 24, 30, 20, 10, 13, 20, 10, 20, 10, 4, 20, 20, 27, 31, 10, 5, 12, 20, 12, 10, 30, 25, 9, 10, 20, 24, 17, 6, 30, 20, 10, 10, 31, 4, 12, 24, 5, 10, 10, 10, 15, 20, 29, 17, 10, 17, 10, 20, 15, 25, 9, 30, 30, 10, 13, 20, 28, 20, 20, 20, 18, 20, 14, 20, 10, 27, 20, 5, 10, 10, 24, 22, 10, 10, 30, 30, 10, 10, 15, 10, 20, 30, 29, 10, 21, 20, 34, 10, 20, 30, 20, 5, 16, 17, 7, 30, 8, 20, 9, 26, 20, 30, 16, 15, 10, 20, 22, 20, 27, 8, 20, 25, 20, 30, 10],
    "service_times": [0, 10, 10, 10, 10, 10, 10, 10, 10, 10, 10, 10, 10, 10, 10, 10, 10, 10, 10, 10, 10, 10, 10, 10, 10, 10, 10, 10, 10, 10, 10, 10, 10, 10, 10, 10, 10, 10, 10, 10, 10, 10, 10, 10, 10, 10, 10, 10, 10, 10, 10, 10, 10, 10, 10, 10, 10, 10, 10, 10, 10, 10, 10, 10, 10, 10, 10, 10, 10, 10, 10, 10, 10, 10, 10, 10, 10, 10, 10, 10, 10, 10, 10, 10, 10, 10, 10, 10, 10, 10, 10, 10, 10, 10, 10, 10, 10, 10, 10, 10, 10, 10, 10, 10, 10, 10, 10, 10, 10, 10, 10, 10, 10, 10, 10, 10, 10, 10, 10, 10, 10, 10, 10, 10, 10, 10, 10, 10, 10, 10, 10, 10, 10, 10, 10, 10, 10, 10, 10, 10, 10, 10, 10, 10, 10, 10, 10, 10, 10, 10, 10, 10, 10, 10, 10, 10, 10, 10, 10, 10, 10, 10, 10, 10, 10, 10, 10, 10, 10, 10, 10, 10, 10, 10, 10, 10, 10, 10, 10, 10, 10, 10, 10, 10, 10, 10, 10, 10, 10, 10, 10, 10, 10, 10, 10, 10, 10, 10, 10, 10, 10, 10, 10, 10, 10, 10, 10, 10, 10, 10, 10, 10, 10, 10, 10, 10, 10, 10, 10, 10, 10, 10, 10, 10, 10, 10, 10, 10, 10, 10, 10, 10, 10, 10, 10, 10, 10, 10, 10, 10, 10, 10, 10, 10, 10, 10, 10, 10, 10, 10, 10, 10, 10, 10, 10, 10, 10, 10, 10, 10, 10, 10, 10, 10, 10, 10, 10, 10, 10, 10, 10, 10, 10, 10, 10, 10, 10, 10, 10, 10, 10, 10, 10, 10, 10, 10, 10, 10, 10, 10, 10, 10, 10, 10, 10, 10, 10, 10, 10, 10, 10, 10, 10, 10, 10, 10, 10, 10, 10, 10, 10, 10, 10, 10, 10, 10, 10, 10, 10, 10, 10, 10, 10, 10, 10, 10, 10, 10, 10, 10, 10, 10, 10, 10, 10, 10, 10, 10, 10, 10, 10, 10, 10, 10, 10, 10, 10, 10, 10, 10, 10, 10, 10, 10, 10, 10, 10, 10, 10, 10, 10, 10, 10, 10, 10, 10, 10, 10, 10, 10, 10, 10, 10, 10, 10, 10, 10, 10, 10, 10, 10, 10, 10, 10, 10, 10, 10, 10, 10, 10, 10, 10, 10, 10, 10, 10, 10, 10, 10, 10, 10, 10, 10, 10, 10, 10, 10, 10, 10, 10, 10, 10, 10, 10, 10, 10, 10, 10, 10, 10, 10, 10, 10, 10, 10, 10, 10, 10, 10, 10, 10, 10, 10, 10, 10, 10, 10, 10, 10, 10, 10, 10, 10, 10, 10, 10, 10, 10, 10, 10, 10, 10, 10, 10, 10, 10, 10, 10, 10, 10, 10, 10, 10, 10, 10, 10, 10, 10, 10, 10, 10, 10, 10, 10, 10, 10, 10, 10, 10, 10, 10, 10, 10, 10, 10, 10, 10, 10, 10, 10, 10, 10, 10, 10, 10, 10, 10, 10, 10, 10, 10, 10, 10, 10, 10, 10, 10, 10, 10, 10, 10, 10, 10, 10, 10, 10, 10, 10, 10, 10, 10, 10, 10, 10, 10, 10, 10, 10, 10, 10, 10, 10, 10, 10, 10, 10, 10, 10, 10, 10, 10, 10, 10, 10, 10, 10, 10, 10, 10, 10, 10, 10, 10, 10, 10, 10, 10, 10, 10, 10, 10, 10, 10, 10, 10, 10, 10, 10, 10, 10, 10, 10, 10, 10, 10, 10, 10, 10, 10, 10, 10, 10, 10, 10, 10, 10, 10, 10, 10, 10, 10, 10, 10, 10, 10, 10, 10, 10, 10, 10, 10, 10, 10, 10, 10, 10, 10, 10, 10, 10, 10, 10, 10, 10, 10, 10, 10, 10, 10, 10, 10, 10, 10, 10, 10, 10, 10, 10, 10, 10, 10, 10, 10, 10, 10, 10, 10, 10, 10, 10, 10, 10, 10, 10, 10, 10, 10, 10, 10, 10, 10, 10, 10, 10, 10, 10, 10, 10, 10, 10, 10, 10, 10, 10, 10, 10, 10, 10, 10, 10, 10, 10, 10, 10, 10, 10, 10, 10, 10, 10, 10, 10, 10, 10, 10, 10, 10, 10, 10, 10, 10, 10, 10, 10, 10, 10, 10, 10, 10, 10, 10, 10, 10, 10, 10, 10, 10, 10, 10, 10, 10, 10, 10, 10, 10, 10, 10, 10, 10, 10, 10, 10, 10, 10, 10, 10, 10, 10, 10, 10, 10, 10, 10, 10, 10, 10, 10, 10, 10, 10, 10, 10, 10, 10, 10, 10, 10, 10, 10, 10, 10, 10, 10, 10, 10, 10, 10, 10, 10, 10, 10, 10, 10, 10, 10, 10, 10, 10, 10, 10, 10, 10, 10, 10, 10, 10, 10, 10, 10, 10, 10, 10, 10, 10, 10, 10, 10, 10, 10, 10, 10, 10, 10, 10, 10, 10, 10, 10, 10, 10, 10, 10, 10, 10, 10, 10, 10, 10, 10, 10, 10, 10, 10, 10, 10, 10, 10, 10, 10, 10, 10, 10, 10, 10, 10, 10, 10, 10, 10, 10, 10, 10, 10, 10, 10, 10, 10, 10, 10, 10, 10, 10, 10, 10, 10, 10, 10, 10, 10, 10, 10, 10, 10, 10, 10, 10, 10, 10, 10, 10, 10, 10, 10, 10, 10, 10, 10, 10, 10, 10, 10, 10, 10, 10, 10, 10, 10, 10, 10, 10, 10, 10, 10, 10, 10, 10, 10, 10, 10, 10, 10, 10, 10, 10, 10, 10, 10, 10, 10, 10, 10, 10, 10, 10, 10, 10, 10, 10, 10, 10, 10, 10, 10, 10, 10, 10, 10, 10, 10, 10, 10, 10, 10, 10, 10, 10, 10, 10, 10, 10, 10, 10, 10, 10, 10, 10, 10, 10, 10, 10, 10, 10, 10, 10, 10, 10, 10, 10, 10, 10, 10, 10, 10, 10, 10, 10, 10, 10, 10, 10, 10, 10, 10, 10, 10, 10, 10, 10, 10, 10, 10, 10, 10, 10, 10, 10, 10, 10, 10, 10, 10, 10, 10, 10, 10, 10, 10, 10, 10, 10, 10, 10, 10, 10, 10, 10, 10, 10, 10, 10, 10],
    "time_windows": [
        [0, 7284],
        [3568, 3688],
        [922, 1042],
        [1419, 1539],
        [3607, 3727],
        [486, 606],
        [243, 363],
        [1842, 1962],
        [3071, 3191],
        [1780, 1900],
        [788, 908],
        [654, 774],
        [1389, 1509],
        [5928, 6048],
        [535, 655],
        [1088, 1208],
        [1129, 1249],
        [635, 755],
        [895, 1015],
        [1379, 1499],
        [1033, 1153],
        [950, 1070],
        [1180, 1300],
        [1252, 1372],
        [2118, 2238],
        [1004, 1124],
        [789, 909],
        [776, 896],
        [3297, 3417],
        [3205, 3325],
        [1999, 2119],
        [1171, 1291],
        [1591, 1711],
        [4017, 4137],
        [3899, 4019],
        [1504, 1624],
        [3760, 3880],
        [973, 1093],
        [536, 656],
        [3326, 3446],
        [790, 910],
        [1373, 1493],
        [3682, 3802],
        [4798, 4918],
        [1023, 1143],
        [1010, 1130],
        [5053, 5173],
        [821, 941],
        [5620, 5740],
        [1284, 1404],
        [1111, 1231],
        [924, 1044],
        [667, 787],
        [6775, 6895],
        [5074, 5194],
        [1328, 1448],
        [1265, 1385],
        [1293, 1413],
        [2307, 2427],
        [450, 570],
        [775, 895],
        [1883, 2003],
        [1533, 1653],
        [580, 700],
        [1598, 1718],
        [666, 786],
        [559, 679],
        [5015, 5135],
        [829, 949],
        [4747, 4867],
        [3297, 3417],
        [940, 1060],
        [3839, 3959],
        [5267, 5387],
        [935, 1055],
        [1066, 1186],
        [2187, 2307],
        [649, 769],
        [5735, 5855],
        [5451, 5571],
        [1938, 2058],
        [834, 954],
        [699, 819],
        [5624, 5744],
        [1391, 1511],
        [2861, 2981],
        [5136, 5256],
        [499, 619],
        [638, 758],
        [1219, 1339],
        [4768, 4888],
        [2554, 2674],
        [4497, 4617],
        [160, 280],
        [5051, 5171],
        [1696, 1816],
        [1147, 1267],
        [1325, 1445],
        [1979, 2099],
        [4364, 4484],
        [1223, 1343],
        [333, 453],
        [1232, 1352],
        [4450, 4570],
        [1309, 1429],
        [866, 986],
        [4518, 4638],
        [695, 815],
        [1731, 1851],
        [6232, 6352],
        [1453, 1573],
        [3284, 3404],
        [2929, 3049],
        [6165, 6285],
        [365, 485],
        [6723, 6843],
        [607, 727],
        [1027, 1147],
        [1222, 1342],
        [3155, 3275],
        [3082, 3202],
        [4489, 4609],
        [1634, 1754],
        [1254, 1374],
        [245, 365],
        [1691, 1811],
        [192, 312],
        [3728, 3848],
        [5092, 5212],
        [3186, 3306],
        [4318, 4438],
        [1792, 1912],
        [5179, 5299],
        [876, 996],
        [814, 934],
        [573, 693],
        [4188, 4308],
        [962, 1082],
        [2614, 2734],
        [1326, 1446],
        [4892, 5012],
        [6302, 6422],
        [1430, 1550],
        [475, 595],
        [592, 712],
        [3319, 3439],
        [822, 942],
        [845, 965],
        [1037, 1157],
        [507, 627],
        [1010, 1130],
        [5732, 5852],
        [1145, 1265],
        [6886, 7006],
        [4099, 4219],
        [741, 861],
        [5528, 5648],
        [1179, 1299],
        [5187, 5307],
        [4404, 4524],
        [1182, 1302],
        [497, 617],
        [519, 639],
        [4405, 4525],
        [1334, 1454],
        [1318, 1438],
        [2871, 2991],
        [1340, 1460],
        [5786, 5906],
        [845, 965],
        [1115, 1235],
        [836, 956],
        [3235, 3355],
        [2975, 3095],
        [1172, 1292],
        [1060, 1180],
        [2, 122],
        [3805, 3925],
        [5916, 6036],
        [935, 1055],
        [1114, 1234],
        [3472, 3592],
        [5644, 5764],
        [1539, 1659],
        [3313, 3433],
        [5164, 5284],
        [4905, 5025],
        [4191, 4311],
        [1191, 1311],
        [1928, 2048],
        [1168, 1288],
        [3611, 3731],
        [4806, 4926],
        [4104, 4224],
        [2396, 2516],
        [1388, 1508],
        [5129, 5249],
        [1435, 1555],
        [1463, 1583],
        [2106, 2226],
        [1618, 1738],
        [1005, 1125],
        [3270, 3390],
        [930, 1050],
        [1307, 1427],
        [4001, 4121],
        [155, 275],
        [4114, 4234],
        [4144, 4264],
        [3584, 3704],
        [903, 1023],
        [1260, 1380],
        [1303, 1423],
        [1518, 1638],
        [5136, 5256],
        [686, 806],
        [658, 778],
        [2257, 2377],
        [5543, 5663],
        [1368, 1488],
        [932, 1052],
        [6184, 6304],
        [4398, 4518],
        [1563, 1683],
        [4682, 4802],
        [532, 652],
        [4427, 4547],
        [774, 894],
        [221, 341],
        [1391, 1511],
        [47, 167],
        [1192, 1312],
        [4241, 4361],
        [867, 987],
        [127, 247],
        [591, 711],
        [3394, 3514],
        [2847, 2967],
        [817, 937],
        [1363, 1483],
        [598, 718],
        [3906, 4026],
        [1287, 1407],
        [1115, 1235],
        [96, 216],
        [1058, 1178],
        [6660, 6780],
        [3467, 3587],
        [324, 444],
        [2103, 2223],
        [5569, 5689],
        [1350, 1470],
        [259, 379],
        [1037, 1157],
        [1636, 1756],
        [3261, 3381],
        [996, 1116],
        [5277, 5397],
        [1616, 1736],
        [5400, 5520],
        [1309, 1429],
        [375, 495],
        [1363, 1483],
        [1784, 1904],
        [643, 763],
        [2234, 2354],
        [1505, 1625],
        [863, 983],
        [1120, 1240],
        [5506, 5626],
        [6055, 6175],
        [396, 516],
        [98, 218],
        [497, 617],
        [1615, 1735],
        [172, 292],
        [1051, 1171],
        [2687, 2807],
        [1470, 1590],
        [1631, 1751],
        [2501, 2621],
        [936, 1056],
        [1511, 1631],
        [4676, 4796],
        [5322, 5442],
        [669, 789],
        [1076, 1196],
        [1285, 1405],
        [1832, 1952],
        [1237, 1357],
        [2032, 2152],
        [5031, 5151],
        [3748, 3868],
        [223, 343],
        [4272, 4392],
        [4345, 4465],
        [5398, 5518],
        [784, 904],
        [754, 874],
        [3127, 3247],
        [604, 724],
        [764, 884],
        [6305, 6425],
        [1205, 1325],
        [586, 706],
        [566, 686],
        [1193, 1313],
        [998, 1118],
        [1194, 1314],
        [1291, 1411],
        [1247, 1367],
        [506, 626],
        [856, 976],
        [5122, 5242],
        [294, 414],
        [777, 897],
        [549, 669],
        [6778, 6898],
        [1353, 1473],
        [1214, 1334],
        [1795, 1915],
        [911, 1031],
        [5394, 5514],
        [1165, 1285],
        [2778, 2898],
        [727, 847],
        [609, 729],
        [646, 766],
        [1286, 1406],
        [880, 1000],
        [1114, 1234],
        [2514, 2634],
        [3928, 4048],
        [3341, 3461],
        [714, 834],
        [1347, 1467],
        [1566, 1686],
        [1588, 1708],
        [5671, 5791],
        [4652, 4772],
        [3529, 3649],
        [771, 891],
        [808, 928],
        [1409, 1529],
        [535, 655],
        [1231, 1351],
        [374, 494],
        [2616, 2736],
        [3215, 3335],
        [236, 356],
        [598, 718],
        [1297, 1417],
        [607, 727],
        [1287, 1407],
        [545, 665],
        [653, 773],
        [1451, 1571],
        [3232, 3352],
        [1499, 1619],
        [2651, 2771],
        [621, 741],
        [1182, 1302],
        [868, 988],
        [441, 561],
        [1076, 1196],
        [1227, 1347],
        [1519, 1639],
        [670, 790],
        [5781, 5901],
        [4579, 4699],
        [517, 637],
        [4550, 4670],
        [2881, 3001],
        [899, 1019],
        [610, 730],
        [686, 806],
        [1294, 1414],
        [1120, 1240],
        [2713, 2833],
        [2988, 3108],
        [1866, 1986],
        [1065, 1185],
        [1279, 1399],
        [937, 1057],
        [5214, 5334],
        [5348, 5468],
        [217, 337],
        [6128, 6248],
        [669, 789],
        [592, 712],
        [2433, 2553],
        [1650, 1770],
        [3426, 3546],
        [442, 562],
        [4516, 4636],
        [563, 683],
        [5226, 5346],
        [1703, 1823],
        [3739, 3859],
        [3178, 3298],
        [3394, 3514],
        [754, 874],
        [547, 667],
        [5367, 5487],
        [1290, 1410],
        [721, 841],
        [5797, 5917],
        [85, 205],
        [939, 1059],
        [1918, 2038],
        [4754, 4874],
        [3101, 3221],
        [3530, 3650],
        [4203, 4323],
        [964, 1084],
        [3138, 3258],
        [949, 1069],
        [4862, 4982],
        [1658, 1778],
        [1037, 1157],
        [6111, 6231],
        [970, 1090],
        [1356, 1476],
        [4660, 4780],
        [978, 1098],
        [2506, 2626],
        [721, 841],
        [5083, 5203],
        [919, 1039],
        [1907, 2027],
        [3976, 4096],
        [1212, 1332],
        [3703, 3823],
        [5949, 6069],
        [4655, 4775],
        [4904, 5024],
        [759, 879],
        [184, 304],
        [5029, 5149],
        [1475, 1595],
        [1031, 1151],
        [903, 1023],
        [3023, 3143],
        [1359, 1479],
        [4086, 4206],
        [1194, 1314],
        [1079, 1199],
        [4513, 4633],
        [968, 1088],
        [728, 848],
        [2960, 3080],
        [112, 232],
        [1168, 1288],
        [419, 539],
        [1602, 1722],
        [1298, 1418],
        [1241, 1361],
        [1116, 1236],
        [2623, 2743],
        [3535, 3655],
        [5212, 5332],
        [1732, 1852],
        [887, 1007],
        [3415, 3535],
        [285, 405],
        [1148, 1268],
        [1149, 1269],
        [2182, 2302],
        [1410, 1530],
        [826, 946],
        [3159, 3279],
        [1033, 1153],
        [845, 965],
        [1424, 1544],
        [844, 964],
        [1961, 2081],
        [299, 419],
        [18, 138],
        [5910, 6030],
        [1118, 1238],
        [1448, 1568],
        [509, 629],
        [2918, 3038],
        [1031, 1151],
        [178, 298],
        [4772, 4892],
        [1376, 1496],
        [881, 1001],
        [1726, 1846],
        [1401, 1521],
        [1352, 1472],
        [1495, 1615],
        [1080, 1200],
        [1698, 1818],
        [2735, 2855],
        [3407, 3527],
        [975, 1095],
        [2255, 2375],
        [3465, 3585],
        [1569, 1689],
        [653, 773],
        [372, 492],
        [4438, 4558],
        [2294, 2414],
        [1336, 1456],
        [2567, 2687],
        [4175, 4295],
        [2144, 2264],
        [482, 602],
        [4781, 4901],
        [1947, 2067],
        [1973, 2093],
        [1372, 1492],
        [1630, 1750],
        [788, 908],
        [862, 982],
        [982, 1102],
        [649, 769],
        [632, 752],
        [2485, 2605],
        [2487, 2607],
        [1207, 1327],
        [916, 1036],
        [814, 934],
        [2877, 2997],
        [1081, 1201],
        [3064, 3184],
        [5281, 5401],
        [725, 845],
        [4789, 4909],
        [981, 1101],
        [6033, 6153],
        [661, 781],
        [542, 662],
        [929, 1049],
        [1423, 1543],
        [6125, 6245],
        [933, 1053],
        [276, 396],
        [828, 948],
        [2189, 2309],
        [5691, 5811],
        [244, 364],
        [1464, 1584],
        [715, 835],
        [724, 844],
        [4056, 4176],
        [166, 286],
        [1291, 1411],
        [815, 935],
        [1543, 1663],
        [3657, 3777],
        [1131, 1251],
        [1233, 1353],
        [1343, 1463],
        [5834, 5954],
        [400, 520],
        [4662, 4782],
        [4170, 4290],
        [3085, 3205],
        [1064, 1184],
        [3230, 3350],
        [3173, 3293],
        [1133, 1253],
        [917, 1037],
        [2522, 2642],
        [4543, 4663],
        [937, 1057],
        [791, 911],
        [1602, 1722],
        [4583, 4703],
        [2022, 2142],
        [1606, 1726],
        [1108, 1228],
        [4094, 4214],
        [1071, 1191],
        [1188, 1308],
        [1712, 1832],
        [439, 559],
        [908, 1028],
        [5417, 5537],
        [426, 546],
        [1188, 1308],
        [4037, 4157],
        [351, 471],
        [1242, 1362],
        [1292, 1412],
        [872, 992],
        [837, 957],
        [1387, 1507],
        [5205, 5325],
        [1006, 1126],
        [1969, 2089],
        [1244, 1364],
        [1361, 1481],
        [5953, 6073],
        [1011, 1131],
        [3704, 3824],
        [1590, 1710],
        [1234, 1354],
        [2990, 3110],
        [1013, 1133],
        [724, 844],
        [1044, 1164],
        [4005, 4125],
        [266, 386],
        [1445, 1565],
        [601, 721],
        [5827, 5947],
        [1127, 1247],
        [730, 850],
        [4744, 4864],
        [863, 983],
        [717, 837],
        [2261, 2381],
        [918, 1038],
        [1421, 1541],
        [1615, 1735],
        [835, 955],
        [3673, 3793],
        [3962, 4082],
        [1190, 1310],
        [4121, 4241],
        [5836, 5956],
        [1489, 1609],
        [1243, 1363],
        [1743, 1863],
        [755, 875],
        [958, 1078],
        [656, 776],
        [993, 1113],
        [4099, 4219],
        [2447, 2567],
        [3124, 3244],
        [1372, 1492],
        [766, 886],
        [787, 907],
        [1275, 1395],
        [1137, 1257],
        [1079, 1199],
        [1101, 1221],
        [4062, 4182],
        [925, 1045],
        [4713, 4833],
        [410, 530],
        [1110, 1230],
        [1984, 2104],
        [435, 555],
        [5026, 5146],
        [3073, 3193],
        [4787, 4907],
        [2827, 2947],
        [3950, 4070],
        [1069, 1189],
        [4503, 4623],
        [2468, 2588],
        [1592, 1712],
        [762, 882],
        [2222, 2342],
        [401, 521],
        [165, 285],
        [5835, 5955],
        [4773, 4893],
        [3027, 3147],
        [1178, 1298],
        [1417, 1537],
        [2126, 2246],
        [2968, 3088],
        [940, 1060],
        [3970, 4090],
        [1022, 1142],
        [1132, 1252],
        [898, 1018],
        [4285, 4405],
        [2349, 2469],
        [1297, 1417],
        [784, 904],
        [3142, 3262],
        [1916, 2036],
        [706, 826],
        [1516, 1636],
        [1189, 1309],
        [1255, 1375],
        [1367, 1487],
        [846, 966],
        [676, 796],
        [472, 592],
        [2513, 2633],
        [4401, 4521],
        [1337, 1457],
        [1154, 1274],
        [1000, 1120],
        [802, 922],
        [1129, 1249],
        [986, 1106],
        [319, 439],
        [1765, 1885],
        [5648, 5768],
        [1365, 1485],
        [1122, 1242],
        [3771, 3891],
        [1476, 1596],
        [941, 1061],
        [1245, 1365],
        [1848, 1968],
        [1054, 1174],
        [280, 400],
        [934, 1054],
        [1574, 1694],
        [973, 1093],
        [926, 1046],
        [3169, 3289],
        [1672, 1792],
        [964, 1084],
        [5530, 5650],
        [1010, 1130],
        [1079, 1199],
        [2348, 2468],
        [3558, 3678],
        [1127, 1247],
        [660, 780],
        [1386, 1506],
        [4663, 4783],
        [3971, 4091],
        [868, 988],
        [705, 825],
        [5904, 6024],
        [133, 253],
        [1171, 1291],
        [1526, 1646],
        [3992, 4112],
        [1112, 1232],
        [951, 1071],
        [978, 1098],
        [2835, 2955],
        [6422, 6542],
        [1159, 1279],
        [1098, 1218],
        [2666, 2786],
        [1340, 1460],
        [1197, 1317],
        [598, 718],
        [985, 1105],
        [1038, 1158],
        [5762, 5882],
        [5135, 5255],
        [1232, 1352],
        [1899, 2019],
        [925, 1045],
        [3764, 3884],
        [2415, 2535],
        [999, 1119],
        [1334, 1454],
        [507, 627],
        [555, 675],
        [777, 897],
        [1173, 1293],
        [6361, 6481],
        [3466, 3586],
        [4285, 4405],
        [537, 657],
        [2597, 2717],
        [901, 1021],
        [437, 557],
        [865, 985],
        [6011, 6131],
        [4897, 5017],
        [812, 932],
        [814, 934],
        [4495, 4615],
        [3705, 3825],
        [340, 460],
        [2399, 2519],
        [1306, 1426],
        [1050, 1170],
        [3118, 3238],
        [952, 1072],
        [1247, 1367],
        [681, 801],
        [96, 216],
        [4265, 4385],
        [3219, 3339],
        [1451, 1571],
        [1643, 1763],
        [967, 1087],
        [4504, 4624],
        [906, 1026],
        [514, 634],
        [1127, 1247],
        [2279, 2399],
        [6107, 6227],
        [741, 861],
        [296, 416],
        [5, 125],
        [2113, 2233],
        [6828, 6948],
        [1382, 1502],
        [898, 1018],
        [877, 997],
        [4940, 5060],
        [902, 1022],
        [6090, 6210],
        [4987, 5107],
        [1105, 1225],
        [4707, 4827],
        [1054, 1174],
        [776, 896],
        [2680, 2800],
        [604, 724],
        [1189, 1309],
        [1074, 1194],
        [926, 1046],
        [1607, 1727],
        [1245, 1365],
        [766, 886],
        [1309, 1429],
        [1461, 1581],
        [420, 540],
        [417, 537],
        [1334, 1454],
        [5035, 5155],
        [1159, 1279],
        [967, 1087],
        [1027, 1147],
        [971, 1091],
        [970, 1090],
        [1641, 1761],
        [921, 1041],
        [1105, 1225],
        [1412, 1532],
        [923, 1043],
        [4891, 5011],
        [3704, 3824],
        [1044, 1164],
        [3267, 3387],
        [905, 1025],
        [6238, 6358],
        [775, 895],
        [139, 259],
        [1085, 1205],
        [2947, 3067],
        [966, 1086],
        [5486, 5606],
        [3431, 3551],
        [1024, 1144],
        [606, 726],
        [1348, 1468],
        [1049, 1169],
        [1669, 1789],
        [950, 1070],
        [388, 508],
        [1167, 1287],
        [1023, 1143],
        [939, 1059],
        [2327, 2447],
        [566, 686],
        [1131, 1251],
        [1480, 1600],
        [1443, 1563],
        [588, 708],
        [1459, 1579],
        [1081, 1201],
        [1656, 1776],
        [2869, 2989],
        [239, 359],
        [4043, 4163],
        [712, 832],
        [872, 992],
        [561, 681],
        [824, 944],
        [667, 787],
        [150, 270],
        [5829, 5949],
        [1645, 1765],
        [967, 1087],
        [891, 1011],
        [869, 989],
        [5002, 5122],
        [811, 931],
        [4220, 4340],
        [1490, 1610],
        [1211, 1331],
        [4256, 4376],
        [886, 1006],
        [839, 959],
        [930, 1050],
        [995, 1115],
        [801, 921],
        [946, 1066],
        [1716, 1836],
        [2516, 2636],
        [1068, 1188],
        [996, 1116],
        [5972, 6092],
        [615, 735],
        [4556, 4676],
        [1345, 1465],
        [1751, 1871],
        [899, 1019],
        [3094, 3214],
        [707, 827],
        [1252, 1372],
        [1083, 1203],
        [1068, 1188],
        [550, 670],
        [1300, 1420],
        [752, 872],
        [4066, 4186],
        [1073, 1193],
        [561, 681],
        [3177, 3297],
        [5476, 5596],
        [5589, 5709],
        [3035, 3155],
        [1557, 1677],
        [1017, 1137],
        [1087, 1207],
        [1104, 1224],
        [2135, 2255],
        [1367, 1487],
        [771, 891],
        [5751, 5871],
        [131, 251],
        [896, 1016],
        [1688, 1808],
        [1021, 1141],
        [5013, 5133],
        [444, 564],
        [2089, 2209],
        [65, 185],
        [869, 989],
        [611, 731],
        [638, 758],
        [761, 881],
        [2572, 2692],
        [4194, 4314],
        [3178, 3298],
        [870, 990],
        [3995, 4115],
        [1724, 1844],
        [4746, 4866],
        [1108, 1228],
        [3428, 3548],
        [1255, 1375],
        [449, 569],
        [1031, 1151],
        [3824, 3944],
        [865, 985],
        [1282, 1402],
        [1463, 1583],
        [1134, 1254],
        [2862, 2982],
        [1402, 1522],
        [3242, 3362],
        [897, 1017],
        [333, 453],
        [3615, 3735],
        [6532, 6652],
        [1016, 1136],
        [750, 870],
        [713, 833],
        [701, 821],
        [1193, 1313],
        [1320, 1440],
        [5599, 5719],
        [1685, 1805],
        [1186, 1306],
        [383, 503],
        [3952, 4072],
        [1520, 1640],
        [5414, 5534],
        [1012, 1132],
        [5370, 5490],
        [1053, 1173],
        [589, 709],
        [1244, 1364],
        [337, 457],
        [2750, 2870],
        [4455, 4575],
        [3328, 3448],
        [1710, 1830],
        [1168, 1288],
        [4009, 4129],
        [388, 508],
        [626, 746],
        [2164, 2284],
        [1435, 1555],
        [1078, 1198],
        [876, 996],
        [326, 446],
        [1237, 1357],
        [210, 330],
        [1882, 2002],
        [1022, 1142],
        [6272, 6392],
        [2765, 2885],
        [980, 1100],
        [4874, 4994],
        [1285, 1405],
        [1241, 1361],
        [895, 1015]
    ],
    "depot": 0,
    "horizon": [0.0, 7284.0],
    "td": {
        "model": "igp-profile",
        "time_periods": [
            [0.0, 1456.8000000000002],
            [1456.8000000000002, 2185.2],
            [2185.2, 5098.799999999999],
            [5098.799999999999, 5827.200000000001],
            [5827.200000000001, 7284.0]
        ],
        "speeds": [
            [0.81, 0.54, 0.81, 0.54, 0.81],
            [1.22, 0.81, 1.22, 0.81, 1.22],
            [1.82, 1.22, 1.82, 1.22, 1.82]
        ],
        "categories_path": "Lera-RC2_10_1.igp.json.gz",
        "categories_sha256": "2bd9cc4eb1b795a89a74ffbebb6d51d24a740bc227d472b8b3290c3b7119d1ba",
        "atf_sha256": "09eecddaa070f06cf979dfc4280020c3456190d75384542e95155c713e1638c1"
    },
    "metadata": {
        "authors": "Florian Rascoussier (0nyr)",
        "base_instance": "Sintef2008/n=1000/RC2_10_1",
        "category_seed": 1140004024919566236,
        "category_seed_recipe": "int.from_bytes(sha256(b'Lera2026:' + base_name)[:8], 'big'); getrandbits(32) % 3 per pair i<j",
        "generated_at": "2026-07-07",
        "generator": {
            "name": "populate_td_lera2026",
            "version": "1",
            "source": "MAMUT-routing benchmarks/VRPTW/Sintef2008 (GehHom1999)"
        },
        "notes": "IGP (Ichoua et al. 2003) speed model: Table 1 scenario S1 (rush factor a=1.5) speeds in the Dabia-2013 five-period skeleton (rush at 20-30% and 70-80% of the original horizon, profile [mid, rush, mid, rush, mid]); categories seeded uniform symmetric, shared across the scenario triplet. Minimal TW repair: deadlines lifted to the earliest TD arrival where the raw port left customers unreachable; l_0 lifted to the worst singleton return; periods anchor to the original horizon. Solomon n=100 IGP instances live in Dabia2013.",
        "scenario": {
            "id": "S1",
            "rush_factor": 1.5
        },
        "tw_repair": {
            "deadlines_lifted": 0,
            "max_deadline_lift": 0,
            "l0_lift": 0
        }
    }
}
