{
    "instance_name": "Lera-RC2_2_9-S2",
    "instance_origin": "GehHom1999",
    "benchmark_name": "Lera2026",
    "num_customers": 200,
    "num_vehicles": 50,
    "vehicle_capacity": 1000,
    "coordinates": [
        [70, 70],
        [10, 86],
        [16, 62],
        [84, 36],
        [79, 72],
        [16, 39],
        [61, 54],
        [96, 26],
        [16, 92],
        [85, 106],
        [6, 25],
        [37, 125],
        [87, 108],
        [18, 104],
        [61, 48],
        [97, 29],
        [112, 67],
        [50, 106],
        [99, 28],
        [15, 9],
        [19, 37],
        [90, 101],
        [125, 68],
        [127, 108],
        [90, 44],
        [4, 23],
        [17, 37],
        [113, 32],
        [63, 57],
        [94, 104],
        [58, 95],
        [137, 96],
        [127, 112],
        [103, 119],
        [20, 69],
        [2, 28],
        [88, 29],
        [86, 102],
        [126, 112],
        [61, 34],
        [113, 69],
        [109, 78],
        [21, 48],
        [86, 36],
        [97, 12],
        [121, 112],
        [19, 39],
        [66, 40],
        [87, 39],
        [63, 50],
        [121, 123],
        [116, 22],
        [137, 101],
        [137, 137],
        [70, 94],
        [117, 92],
        [122, 113],
        [109, 71],
        [35, 102],
        [91, 108],
        [8, 87],
        [140, 42],
        [16, 38],
        [44, 36],
        [60, 84],
        [109, 139],
        [80, 103],
        [66, 82],
        [99, 26],
        [34, 108],
        [135, 65],
        [36, 124],
        [102, 60],
        [30, 21],
        [139, 110],
        [10, 111],
        [18, 70],
        [4, 28],
        [57, 53],
        [54, 41],
        [107, 25],
        [110, 99],
        [84, 88],
        [101, 0],
        [28, 99],
        [119, 114],
        [118, 108],
        [50, 112],
        [44, 116],
        [82, 100],
        [83, 12],
        [126, 23],
        [85, 75],
        [39, 13],
        [120, 136],
        [105, 2],
        [36, 54],
        [35, 90],
        [111, 66],
        [119, 136],
        [84, 99],
        [137, 127],
        [95, 35],
        [69, 6],
        [1, 24],
        [31, 112],
        [138, 78],
        [100, 99],
        [123, 112],
        [119, 130],
        [92, 22],
        [137, 7],
        [121, 124],
        [34, 104],
        [121, 110],
        [56, 139],
        [106, 10],
        [125, 108],
        [21, 115],
        [110, 66],
        [36, 38],
        [56, 129],
        [4, 30],
        [8, 138],
        [88, 35],
        [116, 132],
        [113, 45],
        [28, 107],
        [115, 134],
        [116, 83],
        [57, 59],
        [89, 39],
        [59, 52],
        [112, 71],
        [35, 99],
        [23, 39],
        [84, 39],
        [19, 120],
        [20, 39],
        [90, 104],
        [66, 91],
        [4, 44],
        [78, 63],
        [92, 107],
        [37, 138],
        [120, 14],
        [33, 0],
        [113, 71],
        [112, 13],
        [41, 36],
        [64, 61],
        [121, 134],
        [103, 44],
        [67, 55],
        [86, 80],
        [64, 132],
        [93, 36],
        [115, 124],
        [103, 82],
        [18, 38],
        [122, 131],
        [107, 63],
        [48, 47],
        [62, 58],
        [0, 27],
        [118, 114],
        [91, 95],
        [113, 35],
        [119, 139],
        [104, 54],
        [15, 4],
        [59, 56],
        [21, 44],
        [100, 106],
        [47, 83],
        [34, 72],
        [32, 106],
        [109, 131],
        [89, 24],
        [97, 28],
        [86, 37],
        [1, 34],
        [103, 69],
        [98, 31],
        [103, 34],
        [13, 48],
        [22, 38],
        [61, 59],
        [94, 105],
        [118, 131],
        [108, 30],
        [36, 105],
        [133, 130],
        [15, 18],
        [103, 86],
        [107, 77],
        [99, 34],
        [17, 43],
        [140, 36],
        [26, 105],
        [60, 23]
    ],
    "demands": [0, 14, 15, 10, 22, 20, 10, 10, 10, 20, 10, 10, 20, 18, 20, 30, 10, 25, 30, 2, 20, 10, 20, 10, 6, 10, 30, 36, 10, 10, 35, 9, 20, 18, 13, 10, 33, 10, 10, 7, 20, 21, 10, 20, 10, 20, 10, 20, 20, 10, 9, 32, 12, 27, 32, 25, 20, 20, 10, 10, 17, 13, 20, 9, 23, 8, 15, 27, 40, 10, 3, 34, 30, 12, 19, 21, 26, 10, 10, 9, 13, 21, 16, 9, 10, 20, 10, 18, 27, 18, 29, 13, 37, 20, 10, 1, 15, 20, 20, 30, 20, 28, 10, 8, 10, 20, 43, 17, 20, 20, 18, 40, 21, 10, 30, 18, 13, 20, 10, 10, 5, 21, 40, 10, 20, 10, 4, 20, 30, 30, 10, 23, 20, 20, 20, 20, 20, 16, 10, 20, 16, 24, 19, 30, 5, 20, 20, 10, 27, 13, 20, 20, 12, 10, 21, 8, 20, 11, 27, 30, 20, 30, 19, 20, 30, 10, 20, 9, 20, 13, 23, 20, 20, 10, 1, 21, 10, 20, 15, 20, 10, 20, 30, 20, 30, 15, 20, 20, 10, 20, 18, 20, 13, 10, 19, 34, 9, 10, 1, 40, 16],
    "service_times": [0, 10, 10, 10, 10, 10, 10, 10, 10, 10, 10, 10, 10, 10, 10, 10, 10, 10, 10, 10, 10, 10, 10, 10, 10, 10, 10, 10, 10, 10, 10, 10, 10, 10, 10, 10, 10, 10, 10, 10, 10, 10, 10, 10, 10, 10, 10, 10, 10, 10, 10, 10, 10, 10, 10, 10, 10, 10, 10, 10, 10, 10, 10, 10, 10, 10, 10, 10, 10, 10, 10, 10, 10, 10, 10, 10, 10, 10, 10, 10, 10, 10, 10, 10, 10, 10, 10, 10, 10, 10, 10, 10, 10, 10, 10, 10, 10, 10, 10, 10, 10, 10, 10, 10, 10, 10, 10, 10, 10, 10, 10, 10, 10, 10, 10, 10, 10, 10, 10, 10, 10, 10, 10, 10, 10, 10, 10, 10, 10, 10, 10, 10, 10, 10, 10, 10, 10, 10, 10, 10, 10, 10, 10, 10, 10, 10, 10, 10, 10, 10, 10, 10, 10, 10, 10, 10, 10, 10, 10, 10, 10, 10, 10, 10, 10, 10, 10, 10, 10, 10, 10, 10, 10, 10, 10, 10, 10, 10, 10, 10, 10, 10, 10, 10, 10, 10, 10, 10, 10, 10, 10, 10, 10, 10, 10, 10, 10, 10, 10, 10, 10],
    "time_windows": [
        [0, 2535],
        [1462, 1942],
        [1404, 1884],
        [227, 707],
        [9, 489],
        [144, 624],
        [18, 498],
        [51, 531],
        [1255, 1735],
        [39, 519],
        [341, 821],
        [1194, 1674],
        [51, 531],
        [1167, 1647],
        [90, 570],
        [49, 529],
        [150, 630],
        [1101, 1581],
        [149, 629],
        [1461, 1941],
        [325, 805],
        [441, 921],
        [588, 1068],
        [359, 839],
        [32, 512],
        [290, 770],
        [233, 713],
        [396, 876],
        [14, 494],
        [333, 813],
        [1760, 2240],
        [71, 551],
        [303, 783],
        [1156, 1636],
        [1332, 1812],
        [136, 616],
        [2001, 2481],
        [35, 515],
        [259, 739],
        [1710, 2190],
        [101, 581],
        [771, 1251],
        [53, 533],
        [134, 614],
        [645, 1125],
        [116, 596],
        [373, 853],
        [30, 510],
        [35, 515],
        [39, 519],
        [848, 1328],
        [371, 851],
        [497, 977],
        [219, 699],
        [24, 504],
        [952, 1432],
        [161, 641],
        [39, 519],
        [509, 989],
        [107, 587],
        [1425, 1905],
        [222, 702],
        [188, 668],
        [42, 522],
        [1746, 2226],
        [272, 752],
        [1308, 1788],
        [1824, 2304],
        [101, 581],
        [305, 785],
        [1175, 1655],
        [755, 1235],
        [360, 840],
        [1110, 1590],
        [586, 1066],
        [1791, 2271],
        [1384, 1864],
        [396, 876],
        [197, 677],
        [945, 1425],
        [915, 1395],
        [1031, 1511],
        [1245, 1725],
        [1812, 2292],
        [51, 531],
        [65, 545],
        [519, 999],
        [747, 1227],
        [52, 532],
        [237, 717],
        [741, 1221],
        [874, 1354],
        [15, 495],
        [1323, 1803],
        [278, 758],
        [715, 1195],
        [1308, 1788],
        [1603, 2083],
        [196, 676],
        [234, 714],
        [32, 512],
        [602, 1082],
        [43, 523],
        [152, 632],
        [237, 717],
        [245, 725],
        [629, 1109],
        [1016, 1496],
        [207, 687],
        [432, 912],
        [580, 1060],
        [443, 923],
        [419, 899],
        [408, 888],
        [465, 945],
        [1059, 1539],
        [1015, 1495],
        [407, 887],
        [163, 643],
        [240, 720],
        [1571, 2051],
        [966, 1446],
        [444, 924],
        [985, 1465],
        [85, 565],
        [527, 1007],
        [1016, 1496],
        [81, 561],
        [116, 596],
        [538, 1018],
        [306, 786],
        [36, 516],
        [148, 628],
        [42, 522],
        [561, 1041],
        [1227, 1707],
        [279, 759],
        [865, 1345],
        [417, 897],
        [389, 869],
        [21, 501],
        [1482, 1962],
        [10, 490],
        [153, 633],
        [659, 1139],
        [854, 1334],
        [1750, 2230],
        [53, 533],
        [1920, 2400],
        [44, 524],
        [417, 897],
        [327, 807],
        [42, 522],
        [15, 495],
        [1318, 1798],
        [62, 542],
        [41, 521],
        [1464, 1944],
        [1125, 1605],
        [279, 759],
        [380, 860],
        [297, 777],
        [31, 511],
        [14, 494],
        [185, 665],
        [65, 545],
        [506, 986],
        [55, 535],
        [182, 662],
        [37, 517],
        [223, 703],
        [252, 732],
        [55, 535],
        [225, 705],
        [1091, 1571],
        [2009, 2489],
        [356, 836],
        [72, 552],
        [1024, 1504],
        [49, 529],
        [178, 658],
        [77, 557],
        [33, 513],
        [202, 682],
        [265, 745],
        [1502, 1982],
        [466, 946],
        [362, 842],
        [289, 769],
        [478, 958],
        [203, 683],
        [457, 937],
        [709, 1189],
        [1420, 1900],
        [851, 1331],
        [37, 517],
        [123, 603],
        [87, 567],
        [522, 1002],
        [56, 536],
        [48, 528]
    ],
    "depot": 0,
    "horizon": [0.0, 2535.0],
    "td": {
        "model": "igp-profile",
        "time_periods": [
            [0.0, 507.0],
            [507.0, 760.5],
            [760.5, 1774.5],
            [1774.5, 2028.0],
            [2028.0, 2535.0]
        ],
        "speeds": [
            [0.67, 0.33, 0.67, 0.33, 0.67],
            [1.33, 0.67, 1.33, 0.67, 1.33],
            [2.67, 1.33, 2.67, 1.33, 2.67]
        ],
        "categories_path": "Lera-RC2_2_9.igp.json.gz",
        "categories_sha256": "1415da6cd5bf52478254d091f2c58f0cd1b29dbbe0fbb00585ef209a737f217a",
        "atf_sha256": "9297889e58a66b728699652630fe449967d6d75b6249ae7aa92982c7c1dfe58e"
    },
    "metadata": {
        "authors": "Florian Rascoussier (0nyr)",
        "base_instance": "Sintef2008/n=200/RC2_2_9",
        "category_seed": 2256056176840448756,
        "category_seed_recipe": "int.from_bytes(sha256(b'Lera2026:' + base_name)[:8], 'big'); getrandbits(32) % 3 per pair i<j",
        "generated_at": "2026-07-07",
        "generator": {
            "name": "populate_td_lera2026",
            "version": "1",
            "source": "MAMUT-routing benchmarks/VRPTW/Sintef2008 (GehHom1999)"
        },
        "notes": "IGP (Ichoua et al. 2003) speed model: Table 1 scenario S2 (rush factor a=2.0) speeds in the Dabia-2013 five-period skeleton (rush at 20-30% and 70-80% of the original horizon, profile [mid, rush, mid, rush, mid]); categories seeded uniform symmetric, shared across the scenario triplet. Minimal TW repair: deadlines lifted to the earliest TD arrival where the raw port left customers unreachable; l_0 lifted to the worst singleton return; periods anchor to the original horizon. Solomon n=100 IGP instances live in Dabia2013.",
        "scenario": {
            "id": "S2",
            "rush_factor": 2.0
        },
        "tw_repair": {
            "deadlines_lifted": 0,
            "max_deadline_lift": 0,
            "l0_lift": 0
        }
    }
}
